pkg/__init__.py
closet_viewer_cv-0.0.6.dist-info/LICENSE
closet_viewer_cv-0.0.6.dist-info/METADATA
closet_viewer_cv-0.0.6.dist-info/WHEEL
closet_viewer_cv-0.0.6.dist-info/entry_points.txt
closet_viewer_cv-0.0.6.dist-info/top_level.txt
closet_viewer_cv-0.0.6.dist-info/RECORD
