Metadata-Version: 2.1
Name: closet-viewer-cv
Version: 0.0.6
Summary: A small example package
Home-page: https://github.com/pypa/sampleproject
Author: Ingun Jon
Author-email: ingun37@gmail.com
License: UNKNOWN
Platform: UNKNOWN
Classifier: Programming Language :: Python :: 3
Classifier: License :: OSI Approved :: MIT License
Classifier: Operating System :: OS Independent
Requires-Python: >=3.7
Requires-Dist: opencv-python
